sql_storage_operations_ivy/__init__.py
sql_storage_operations_ivy/create.py
sql_storage_operations_ivy/pg_storage.py
sql_storage_operations_ivy/sqlite_storage.py
sql_storage_operations_ivy-1.0.0.dist-info/LICENSE
sql_storage_operations_ivy-1.0.0.dist-info/METADATA
sql_storage_operations_ivy-1.0.0.dist-info/WHEEL
sql_storage_operations_ivy-1.0.0.dist-info/RECORD
